odoo/addons/sale_commission_partial_settlement/README.rst
odoo/addons/sale_commission_partial_settlement/__init__.py
odoo/addons/sale_commission_partial_settlement/__manifest__.py
odoo/addons/sale_commission_partial_settlement/i18n/es.po
odoo/addons/sale_commission_partial_settlement/i18n/it.po
odoo/addons/sale_commission_partial_settlement/i18n/sale_commission_partial_settlement.pot
odoo/addons/sale_commission_partial_settlement/migrations/14.0.1.0.1/post-migrate.py
odoo/addons/sale_commission_partial_settlement/migrations/14.0.1.1.0/post-migrate.py
odoo/addons/sale_commission_partial_settlement/models/__init__.py
odoo/addons/sale_commission_partial_settlement/models/account_invoice_line_agent.py
odoo/addons/sale_commission_partial_settlement/models/account_invoice_line_agent_partial.py
odoo/addons/sale_commission_partial_settlement/models/account_partial_reconcile.py
odoo/addons/sale_commission_partial_settlement/models/res_company.py
odoo/addons/sale_commission_partial_settlement/models/res_config_settings.py
odoo/addons/sale_commission_partial_settlement/models/sale_commission.py
odoo/addons/sale_commission_partial_settlement/models/sale_commission_settlement.py
odoo/addons/sale_commission_partial_settlement/models/sale_commission_settlement_line.py
odoo/addons/sale_commission_partial_settlement/readme/CONTRIBUTORS.rst
odoo/addons/sale_commission_partial_settlement/readme/DESCRIPTION.rst
odoo/addons/sale_commission_partial_settlement/readme/USAGE.rst
odoo/addons/sale_commission_partial_settlement/security/ir.model.access.csv
odoo/addons/sale_commission_partial_settlement/static/description/icon.png
odoo/addons/sale_commission_partial_settlement/static/description/index.html
odoo/addons/sale_commission_partial_settlement/tests/__init__.py
odoo/addons/sale_commission_partial_settlement/tests/test_partial_settlement.py
odoo/addons/sale_commission_partial_settlement/views/res_config_settings_view.xml
odoo14_addon_sale_commission_partial_settlement-14.0.1.2.0.dist-info/METADATA
odoo14_addon_sale_commission_partial_settlement-14.0.1.2.0.dist-info/WHEEL
odoo14_addon_sale_commission_partial_settlement-14.0.1.2.0.dist-info/top_level.txt
odoo14_addon_sale_commission_partial_settlement-14.0.1.2.0.dist-info/RECORD
